niu/__init__.py
niu/niu.py
niu-0.2.7.dist-info/LICENSE
niu-0.2.7.dist-info/METADATA
niu-0.2.7.dist-info/WHEEL
niu-0.2.7.dist-info/top_level.txt
niu-0.2.7.dist-info/RECORD
