Metadata-Version: 2.1
Name: niu
Version: 0.2.7
Summary: NIU cloud interface library
Home-page: https://github.com/Bonnee/niu
Author: Matteo Bonora
Author-email: bonora.matteo@gmail.com
License: UNKNOWN
Platform: UNKNOWN
Classifier: Programming Language :: Python :: 3
Classifier: License :: OSI Approved :: Apache Software License
Classifier: Operating System :: OS Independent
Classifier: Intended Audience :: Developers
Requires-Python: >=3.6
